{
    "Formula": "Na3VSe4",
    "matID": "06705252",
    "Source": "oqmd",
    "Point Group": "-43m",
    "Space Group": "I-43m",
    "poscar": "Na3 V1 Se4\n1.0\n  -3.6829677512224097    3.6829677512224097    3.6829677512224097\n   3.6829677512224097   -3.6829677512224097    3.6829677512224097\n   3.6829677512224097    3.6829677512224097   -3.6829677512224097\nNa V Se\n3 1 4\ndirect\n   0.5000000000000000    0.5000000000000000   -0.0000000000000000 Na\n   0.0000000000000000    0.5000000000000000    0.5000000000000000 Na\n   0.5000000000000000    0.0000000000000000    0.5000000000000000 Na\n   0.0000000000000000    0.0000000000000000   -0.0000000000000000 V\n   0.6383621316387472    0.0000000000000000    0.0000000000000000 Se\n   0.0000000000000000    0.6383621316387472    0.0000000000000000 Se\n   0.3616378683612527    0.3616378683612527    0.3616378683612527 Se\n   0.0000000000000000   -0.0000000000000000    0.6383621316387472 Se\n",
    "cif": "# generated using pymatgen\ndata_Na3VSe4\n_symmetry_space_group_name_H-M   'P 1'\n_cell_length_a   6.37908727\n_cell_length_b   6.37908727\n_cell_length_c   6.37908727\n_cell_angle_alpha   109.47122063\n_cell_angle_beta   109.47122063\n_cell_angle_gamma   109.47122063\n_symmetry_Int_Tables_number   1\n_chemical_formula_structural   Na3VSe4\n_chemical_formula_sum   'Na3 V1 Se4'\n_cell_volume   199.82680274\n_cell_formula_units_Z   1\nloop_\n _symmetry_equiv_pos_site_id\n _symmetry_equiv_pos_as_xyz\n  1  'x, y, z'\nloop_\n _atom_site_type_symbol\n _atom_site_label\n _atom_site_symmetry_multiplicity\n _atom_site_fract_x\n _atom_site_fract_y\n _atom_site_fract_z\n _atom_site_occupancy\n  Na  Na0  1  0.50000000  0.50000000  -0.00000000  1\n  Na  Na1  1  0.00000000  0.50000000  0.50000000  1\n  Na  Na2  1  0.50000000  0.00000000  0.50000000  1\n  V  V3  1  0.00000000  0.00000000  -0.00000000  1\n  Se  Se4  1  0.63836213  0.00000000  0.00000000  1\n  Se  Se5  1  0.00000000  0.63836213  0.00000000  1\n  Se  Se6  1  0.36163787  0.36163787  0.36163787  1\n  Se  Se7  1  0.00000000  -0.00000000  0.63836213  1\n",
    "abc": [
        6.37909,
        6.37909,
        6.37909
    ],
    "angles": [
        109.47122,
        109.47122,
        109.47122
    ],
    "eij": [
        [
            0.0,
            -0.0,
            -0.0,
            -0.82771,
            0.0,
            0.0
        ],
        [
            -0.0,
            0.0,
            -0.0,
            0.0,
            -0.82771,
            0.0
        ],
        [
            0.0,
            0.0,
            -0.0,
            0.0,
            0.0,
            -0.82772
        ]
    ],
    "Cij": [
        [
            38.252179999999996,
            13.339789999999999,
            13.339789999999999,
            0.0,
            0.0,
            0.0
        ],
        [
            13.339789999999999,
            38.252179999999996,
            13.339789999999999,
            0.0,
            0.0,
            0.0
        ],
        [
            13.339789999999999,
            13.339789999999999,
            38.252179999999996,
            0.0,
            0.0,
            0.0
        ],
        [
            0.0,
            0.0,
            0.0,
            0.63875,
            0.0,
            0.0
        ],
        [
            0.0,
            0.0,
            0.0,
            0.0,
            0.63875,
            0.0
        ],
        [
            0.0,
            0.0,
            0.0,
            0.0,
            0.0,
            0.63875
        ]
    ],
    "Sij": [
        [
            0.031894040586301076,
            -0.008246628374003421,
            -0.00824662837400342,
            0.0,
            0.0,
            0.0
        ],
        [
            -0.008246628374003421,
            0.031894040586301076,
            -0.008246628374003421,
            0.0,
            0.0,
            0.0
        ],
        [
            -0.00824662837400342,
            -0.00824662837400342,
            0.031894040586301076,
            0.0,
            0.0,
            0.0
        ],
        [
            0.0,
            0.0,
            0.0,
            1.5655577299412915,
            0.0,
            0.0
        ],
        [
            0.0,
            0.0,
            0.0,
            0.0,
            1.5655577299412915,
            0.0
        ],
        [
            0.0,
            0.0,
            0.0,
            0.0,
            0.0,
            1.5655577299412915
        ]
    ],
    "dij": [
        [
            0.0,
            0.0,
            0.0,
            -1295.8277886497062,
            0.0,
            0.0
        ],
        [
            0.0,
            0.0,
            0.0,
            0.0,
            -1295.8277886497062,
            0.0
        ],
        [
            0.0,
            0.0,
            0.0,
            0.0,
            0.0,
            -1295.8434442270059
        ]
    ],
    "poisson": [
        0.2585632996762869,
        0.2585632996762869,
        0.25856329967628683
    ]
}