{
    "Formula": "YAs",
    "matID": "11483784",
    "Source": "oqmd",
    "Point Group": "-43m",
    "Space Group": "F-43m",
    "poscar": "Y1 As1\n1.0\n  -0.0000000000000000    3.2360507334660542    3.2360507334660542\n   3.2360507334660542    0.0000000000000000    3.2360507334660542\n   3.2360507334660542    3.2360507334660542    0.0000000000000000\nY As\n1 1\ndirect\n   0.7500000000000000    0.7500000000000000    0.7500000000000000 Y\n   0.5000000000000000    0.5000000000000000    0.5000000000000000 As\n",
    "cif": "# generated using pymatgen\ndata_YAs\n_symmetry_space_group_name_H-M   'P 1'\n_cell_length_a   4.57646684\n_cell_length_b   4.57646684\n_cell_length_c   4.57646684\n_cell_angle_alpha   60.00000000\n_cell_angle_beta   60.00000000\n_cell_angle_gamma   60.00000000\n_symmetry_Int_Tables_number   1\n_chemical_formula_structural   YAs\n_chemical_formula_sum   'Y1 As1'\n_cell_volume   67.77600415\n_cell_formula_units_Z   1\nloop_\n _symmetry_equiv_pos_site_id\n _symmetry_equiv_pos_as_xyz\n  1  'x, y, z'\nloop_\n _atom_site_type_symbol\n _atom_site_label\n _atom_site_symmetry_multiplicity\n _atom_site_fract_x\n _atom_site_fract_y\n _atom_site_fract_z\n _atom_site_occupancy\n  Y  Y0  1  0.75000000  0.75000000  0.75000000  1\n  As  As1  1  0.50000000  0.50000000  0.50000000  1\n",
    "abc": [
        4.57647,
        4.57647,
        4.57647
    ],
    "angles": [
        60.0,
        60.0,
        60.0
    ],
    "eij": [
        [
            0.0,
            0.0,
            0.0,
            -0.30829,
            0.0,
            0.0
        ],
        [
            0.0,
            0.0,
            0.0,
            0.0,
            -0.30828,
            0.0
        ],
        [
            0.0,
            0.0,
            0.0,
            0.0,
            0.0,
            -0.30829
        ]
    ],
    "Cij": [
        [
            53.76585,
            46.78913,
            46.78913,
            0.0,
            0.0,
            0.0
        ],
        [
            46.78913,
            53.76585,
            46.78913,
            0.0,
            0.0,
            0.0
        ],
        [
            46.78913,
            46.78913,
            53.76585,
            0.0,
            0.0,
            0.0
        ],
        [
            0.0,
            0.0,
            0.0,
            10.69686,
            0.0,
            0.0
        ],
        [
            0.0,
            0.0,
            0.0,
            0.0,
            10.69686,
            0.0
        ],
        [
            0.0,
            0.0,
            0.0,
            0.0,
            0.0,
            10.69686
        ]
    ],
    "Sij": [
        [
            0.09781816478101604,
            -0.04551566544292866,
            -0.04551566544292862,
            0.0,
            0.0,
            0.0
        ],
        [
            -0.04551566544292865,
            0.09781816478101608,
            -0.045515665442928684,
            0.0,
            0.0,
            0.0
        ],
        [
            -0.04551566544292863,
            -0.04551566544292868,
            0.09781816478101606,
            0.0,
            0.0,
            0.0
        ],
        [
            0.0,
            0.0,
            0.0,
            0.09348537795203453,
            0.0,
            0.0
        ],
        [
            0.0,
            0.0,
            0.0,
            0.0,
            0.09348537795203453,
            0.0
        ],
        [
            0.0,
            0.0,
            0.0,
            0.0,
            0.0,
            0.09348537795203453
        ]
    ],
    "dij": [
        [
            0.0,
            0.0,
            0.0,
            -28.820607168832726,
            0.0,
            0.0
        ],
        [
            0.0,
            0.0,
            0.0,
            0.0,
            -28.819672315053204,
            0.0
        ],
        [
            0.0,
            0.0,
            0.0,
            0.0,
            0.0,
            -28.820607168832726
        ]
    ],
    "poisson": [
        0.46530892850856315,
        0.4653089285085635,
        0.465308928508563
    ]
}