{
    "Formula": "NbAu3Se4",
    "matID": "23331994",
    "Source": "oqmd",
    "Point Group": "-43m",
    "Space Group": "P-43m",
    "poscar": "Nb1 Au3 Se4\n1.0\n   6.1277733048665972    0.0000000000000000    0.0000000000000000\n   0.0000000000000000    6.1277733048665972    0.0000000000000000\n  -0.0000000000000000   -0.0000000000000000    6.1277733048665972\nNb Au Se\n1 3 4\ndirect\n  -0.0000000000000000   -0.0000000000000000   -0.0000000000000000 Nb\n   0.5000000000000000   -0.0000000000000000   -0.0000000000000000 Au\n  -0.0000000000000000    0.5000000000000000   -0.0000000000000000 Au\n  -0.0000000000000000   -0.0000000000000000    0.5000000000000000 Au\n   0.2379872557357119    0.2379872557357119    0.2379872557357119 Se\n   0.7620127442642881    0.7620127442642881    0.2379872557357119 Se\n   0.7620127442642881    0.2379872557357119    0.7620127442642881 Se\n   0.2379872557357119    0.7620127442642881    0.7620127442642881 Se\n",
    "cif": "# generated using pymatgen\ndata_NbAu3Se4\n_symmetry_space_group_name_H-M   'P 1'\n_cell_length_a   6.12777330\n_cell_length_b   6.12777330\n_cell_length_c   6.12777330\n_cell_angle_alpha   90.00000000\n_cell_angle_beta   90.00000000\n_cell_angle_gamma   90.00000000\n_symmetry_Int_Tables_number   1\n_chemical_formula_structural   NbAu3Se4\n_chemical_formula_sum   'Nb1 Au3 Se4'\n_cell_volume   230.09547127\n_cell_formula_units_Z   1\nloop_\n _symmetry_equiv_pos_site_id\n _symmetry_equiv_pos_as_xyz\n  1  'x, y, z'\nloop_\n _atom_site_type_symbol\n _atom_site_label\n _atom_site_symmetry_multiplicity\n _atom_site_fract_x\n _atom_site_fract_y\n _atom_site_fract_z\n _atom_site_occupancy\n  Nb  Nb0  1  -0.00000000  -0.00000000  -0.00000000  1\n  Au  Au1  1  0.50000000  -0.00000000  -0.00000000  1\n  Au  Au2  1  -0.00000000  0.50000000  -0.00000000  1\n  Au  Au3  1  -0.00000000  -0.00000000  0.50000000  1\n  Se  Se4  1  0.23798726  0.23798726  0.23798726  1\n  Se  Se5  1  0.76201274  0.76201274  0.23798726  1\n  Se  Se6  1  0.76201274  0.23798726  0.76201274  1\n  Se  Se7  1  0.23798726  0.76201274  0.76201274  1\n",
    "abc": [
        6.12777,
        6.12777,
        6.12777
    ],
    "angles": [
        90.0,
        90.0,
        90.0
    ],
    "eij": [
        [
            -0.0,
            -0.0,
            -0.0,
            0.13233,
            0.0,
            0.0
        ],
        [
            -0.0,
            -0.0,
            -0.0,
            0.0,
            0.13233,
            0.0
        ],
        [
            -0.0,
            -0.0,
            -0.0,
            0.0,
            0.0,
            0.13233
        ]
    ],
    "Cij": [
        [
            63.05651,
            16.762880000000003,
            16.762880000000003,
            0.0,
            0.0,
            0.0
        ],
        [
            16.762880000000003,
            63.05651,
            16.762880000000003,
            0.0,
            0.0,
            0.0
        ],
        [
            16.762880000000003,
            16.762880000000003,
            63.05651,
            0.0,
            0.0,
            0.0
        ],
        [
            0.0,
            0.0,
            0.0,
            13.226499999999998,
            0.0,
            0.0
        ],
        [
            0.0,
            0.0,
            0.0,
            0.0,
            13.226499999999998,
            0.0
        ],
        [
            0.0,
            0.0,
            0.0,
            0.0,
            0.0,
            13.226499999999998
        ]
    ],
    "Sij": [
        [
            0.017852118448017,
            -0.0037491256108308406,
            -0.0037491256108308415,
            0.0,
            0.0,
            0.0
        ],
        [
            -0.0037491256108308415,
            0.01785211844801699,
            -0.0037491256108308415,
            0.0,
            0.0,
            0.0
        ],
        [
            -0.003749125610830841,
            -0.0037491256108308415,
            0.017852118448016995,
            0.0,
            0.0,
            0.0
        ],
        [
            0.0,
            0.0,
            0.0,
            0.07560579140362153,
            0.0,
            0.0
        ],
        [
            0.0,
            0.0,
            0.0,
            0.0,
            0.07560579140362153,
            0.0
        ],
        [
            0.0,
            0.0,
            0.0,
            0.0,
            0.0,
            0.07560579140362153
        ]
    ],
    "dij": [
        [
            0.0,
            0.0,
            0.0,
            10.004914376441238,
            0.0,
            0.0
        ],
        [
            0.0,
            0.0,
            0.0,
            0.0,
            10.004914376441238,
            0.0
        ],
        [
            0.0,
            0.0,
            0.0,
            0.0,
            0.0,
            10.004914376441238
        ]
    ],
    "poisson": [
        0.2100101241064358,
        0.21001012410643582,
        0.21001012410643574
    ]
}