{
    "Formula": "LiMgSb",
    "matID": "35428394",
    "Source": "jarvis",
    "Point Group": "-43m",
    "Space Group": "F-43m",
    "poscar": "Li1 Mg1 Sb1\n1.0\n   0.0000000000000000    3.3347416070470746    3.3347416070470746\n   3.3347416070470746    0.0000000000000000    3.3347416070470746\n   3.3347416070470746    3.3347416070470746    0.0000000000000000\nLi Mg Sb\n1 1 1\ndirect\n   0.5000000000000000    0.5000000000000000    0.5000000000000000 Li\n   0.0000000000000000    0.0000000000000000    0.0000000000000000 Mg\n   0.7500000000000000    0.7500000000000000    0.7500000000000000 Sb\n",
    "cif": "# generated using pymatgen\ndata_LiMgSb\n_symmetry_space_group_name_H-M   'P 1'\n_cell_length_a   4.71603681\n_cell_length_b   4.71603681\n_cell_length_c   4.71603681\n_cell_angle_alpha   60.00000000\n_cell_angle_beta   60.00000000\n_cell_angle_gamma   60.00000000\n_symmetry_Int_Tables_number   1\n_chemical_formula_structural   LiMgSb\n_chemical_formula_sum   'Li1 Mg1 Sb1'\n_cell_volume   74.16799866\n_cell_formula_units_Z   1\nloop_\n _symmetry_equiv_pos_site_id\n _symmetry_equiv_pos_as_xyz\n  1  'x, y, z'\nloop_\n _atom_site_type_symbol\n _atom_site_label\n _atom_site_symmetry_multiplicity\n _atom_site_fract_x\n _atom_site_fract_y\n _atom_site_fract_z\n _atom_site_occupancy\n  Li  Li0  1  0.50000000  0.50000000  0.50000000  1\n  Mg  Mg1  1  0.00000000  0.00000000  0.00000000  1\n  Sb  Sb2  1  0.75000000  0.75000000  0.75000000  1\n",
    "abc": [
        4.71604,
        4.71604,
        4.71604
    ],
    "angles": [
        60.0,
        60.0,
        60.0
    ],
    "eij": [
        [
            0.0,
            0.0,
            0.0,
            -0.00643,
            0.0,
            0.0
        ],
        [
            0.0,
            0.0,
            0.0,
            0.0,
            -0.00643,
            0.0
        ],
        [
            0.0,
            0.0,
            0.0,
            0.0,
            0.0,
            -0.00643
        ]
    ],
    "Cij": [
        [
            65.83318,
            22.36608,
            22.36608,
            0.0,
            0.0,
            0.0
        ],
        [
            22.36608,
            65.83318,
            22.36608,
            0.0,
            0.0,
            0.0
        ],
        [
            22.36608,
            22.36608,
            65.83318,
            0.0,
            0.0,
            0.0
        ],
        [
            0.0,
            0.0,
            0.0,
            29.058819999999997,
            0.0,
            0.0
        ],
        [
            0.0,
            0.0,
            0.0,
            0.0,
            29.058819999999997,
            0.0
        ],
        [
            0.0,
            0.0,
            0.0,
            0.0,
            0.0,
            29.058819999999997
        ]
    ],
    "Sij": [
        [
            0.01835207896939982,
            -0.004653826646571797,
            -0.004653826646571797,
            0.0,
            0.0,
            0.0
        ],
        [
            -0.004653826646571797,
            0.018352078969399825,
            -0.004653826646571797,
            0.0,
            0.0,
            0.0
        ],
        [
            -0.004653826646571797,
            -0.004653826646571797,
            0.018352078969399825,
            0.0,
            0.0,
            0.0
        ],
        [
            0.0,
            0.0,
            0.0,
            0.034412959645298745,
            0.0,
            0.0
        ],
        [
            0.0,
            0.0,
            0.0,
            0.0,
            0.034412959645298745,
            0.0
        ],
        [
            0.0,
            0.0,
            0.0,
            0.0,
            0.0,
            0.034412959645298745
        ]
    ],
    "dij": [
        [
            0.0,
            0.0,
            0.0,
            -0.22127533051927095,
            0.0,
            0.0
        ],
        [
            0.0,
            0.0,
            0.0,
            0.0,
            -0.22127533051927095,
            0.0
        ],
        [
            0.0,
            0.0,
            0.0,
            0.0,
            0.0,
            -0.22127533051927095
        ]
    ],
    "poisson": [
        0.2535858010600089,
        0.2535858010600089,
        0.25358580106000894
    ]
}