{
    "Formula": "MgZrSiOs",
    "matID": "38925263",
    "Source": "oqmd",
    "Point Group": "-43m",
    "Space Group": "F-43m",
    "poscar": "Mg1 Zr1 Si1 Os1\n1.0\n   0.0000000000000000    3.1734523568669699    3.1734523568669699\n   3.1734523568669699    0.0000000000000000    3.1734523568669699\n   3.1734523568669699    3.1734523568669699   -0.0000000000000000\nMg Zr Si Os\n1 1 1 1\ndirect\n   0.7500000000000000    0.7500000000000000    0.7500000000000000 Mg\n  -0.0000000000000000    0.0000000000000000   -0.0000000000000000 Zr\n   0.5000000000000000    0.5000000000000000    0.5000000000000000 Si\n   0.2500000000000000    0.2500000000000000    0.2500000000000000 Os\n",
    "cif": "# generated using pymatgen\ndata_MgZrSiOs\n_symmetry_space_group_name_H-M   'P 1'\n_cell_length_a   4.48793936\n_cell_length_b   4.48793936\n_cell_length_c   4.48793936\n_cell_angle_alpha   60.00000000\n_cell_angle_beta   60.00000000\n_cell_angle_gamma   60.00000000\n_symmetry_Int_Tables_number   1\n_chemical_formula_structural   MgZrSiOs\n_chemical_formula_sum   'Mg1 Zr1 Si1 Os1'\n_cell_volume   63.91840711\n_cell_formula_units_Z   1\nloop_\n _symmetry_equiv_pos_site_id\n _symmetry_equiv_pos_as_xyz\n  1  'x, y, z'\nloop_\n _atom_site_type_symbol\n _atom_site_label\n _atom_site_symmetry_multiplicity\n _atom_site_fract_x\n _atom_site_fract_y\n _atom_site_fract_z\n _atom_site_occupancy\n  Mg  Mg0  1  0.75000000  0.75000000  0.75000000  1\n  Zr  Zr1  1  -0.00000000  0.00000000  -0.00000000  1\n  Si  Si2  1  0.50000000  0.50000000  0.50000000  1\n  Os  Os3  1  0.25000000  0.25000000  0.25000000  1\n",
    "abc": [
        4.48794,
        4.48794,
        4.48794
    ],
    "angles": [
        60.0,
        60.0,
        60.0
    ],
    "eij": [
        [
            0.0,
            0.0,
            0.0,
            2.41946,
            0.0,
            0.0
        ],
        [
            0.0,
            0.0,
            0.0,
            0.0,
            2.41946,
            0.0
        ],
        [
            0.0,
            0.0,
            0.0,
            0.0,
            0.0,
            2.41946
        ]
    ],
    "Cij": [
        [
            186.24307,
            146.08508,
            146.08508,
            0.0,
            0.0,
            0.0
        ],
        [
            146.08508,
            186.24307,
            146.08508,
            0.0,
            0.0,
            0.0
        ],
        [
            146.08508,
            146.08508,
            186.24307,
            0.0,
            0.0,
            0.0
        ],
        [
            0.0,
            0.0,
            0.0,
            74.57682,
            0.0,
            0.0
        ],
        [
            0.0,
            0.0,
            0.0,
            0.0,
            74.57682,
            0.0
        ],
        [
            0.0,
            0.0,
            0.0,
            0.0,
            0.0,
            74.57682
        ]
    ],
    "Sij": [
        [
            0.01729784421859945,
            -0.007603800510133247,
            -0.007603800510133249,
            0.0,
            0.0,
            0.0
        ],
        [
            -0.007603800510133246,
            0.01729784421859945,
            -0.007603800510133249,
            0.0,
            0.0,
            0.0
        ],
        [
            -0.007603800510133248,
            -0.007603800510133249,
            0.017297844218599454,
            0.0,
            0.0,
            0.0
        ],
        [
            0.0,
            0.0,
            0.0,
            0.013408992231098081,
            0.0,
            0.0
        ],
        [
            0.0,
            0.0,
            0.0,
            0.0,
            0.013408992231098081,
            0.0
        ],
        [
            0.0,
            0.0,
            0.0,
            0.0,
            0.0,
            0.013408992231098081
        ]
    ],
    "dij": [
        [
            0.0,
            0.0,
            0.0,
            32.44252034345256,
            0.0,
            0.0
        ],
        [
            0.0,
            0.0,
            0.0,
            0.0,
            32.44252034345256,
            0.0
        ],
        [
            0.0,
            0.0,
            0.0,
            0.0,
            0.0,
            32.44252034345256
        ]
    ],
    "poisson": [
        0.4395808179355255,
        0.4395808179355255,
        0.43958081793552556
    ]
}