{
    "Formula": "LiTaRuPb",
    "matID": "60875092",
    "Source": "oqmd",
    "Point Group": "-43m",
    "Space Group": "F-43m",
    "poscar": "Li1 Ta1 Ru1 Pb1\n1.0\n   0.0000000000000000    3.2052892861716513    3.2052892861716513\n   3.2052892861716513    0.0000000000000000    3.2052892861716513\n   3.2052892861716513    3.2052892861716513    0.0000000000000000\nLi Ta Ru Pb\n1 1 1 1\ndirect\n   0.7500000000000000    0.7500000000000000    0.7500000000000000 Li\n   0.5000000000000000    0.5000000000000000    0.5000000000000000 Ta\n   0.2500000000000000    0.2500000000000000    0.2500000000000000 Ru\n   0.0000000000000000   -0.0000000000000000    0.0000000000000000 Pb\n",
    "cif": "# generated using pymatgen\ndata_LiTaRuPb\n_symmetry_space_group_name_H-M   'P 1'\n_cell_length_a   4.53296358\n_cell_length_b   4.53296358\n_cell_length_c   4.53296358\n_cell_angle_alpha   60.00000000\n_cell_angle_beta   60.00000000\n_cell_angle_gamma   60.00000000\n_symmetry_Int_Tables_number   1\n_chemical_formula_structural   LiTaRuPb\n_chemical_formula_sum   'Li1 Ta1 Ru1 Pb1'\n_cell_volume   65.86151119\n_cell_formula_units_Z   1\nloop_\n _symmetry_equiv_pos_site_id\n _symmetry_equiv_pos_as_xyz\n  1  'x, y, z'\nloop_\n _atom_site_type_symbol\n _atom_site_label\n _atom_site_symmetry_multiplicity\n _atom_site_fract_x\n _atom_site_fract_y\n _atom_site_fract_z\n _atom_site_occupancy\n  Li  Li0  1  0.75000000  0.75000000  0.75000000  1\n  Ta  Ta1  1  0.50000000  0.50000000  0.50000000  1\n  Ru  Ru2  1  0.25000000  0.25000000  0.25000000  1\n  Pb  Pb3  1  0.00000000  -0.00000000  0.00000000  1\n",
    "abc": [
        4.53296,
        4.53296,
        4.53296
    ],
    "angles": [
        60.0,
        60.0,
        60.0
    ],
    "eij": [
        [
            0.0,
            0.0,
            0.0,
            2.66461,
            0.0,
            0.0
        ],
        [
            0.0,
            0.0,
            0.0,
            0.0,
            2.66461,
            0.0
        ],
        [
            0.0,
            0.0,
            0.0,
            0.0,
            0.0,
            2.66461
        ]
    ],
    "Cij": [
        [
            203.40723,
            119.67763,
            119.67763,
            0.0,
            0.0,
            0.0
        ],
        [
            119.67763,
            203.40723,
            119.67763,
            0.0,
            0.0,
            0.0
        ],
        [
            119.67763,
            119.67763,
            203.40723,
            0.0,
            0.0,
            0.0
        ],
        [
            0.0,
            0.0,
            0.0,
            64.60733,
            0.0,
            0.0
        ],
        [
            0.0,
            0.0,
            0.0,
            0.0,
            64.60733,
            0.0
        ],
        [
            0.0,
            0.0,
            0.0,
            0.0,
            0.0,
            64.60733
        ]
    ],
    "Sij": [
        [
            0.00871498751947037,
            -0.0032282201394698367,
            -0.0032282201394698367,
            0.0,
            0.0,
            0.0
        ],
        [
            -0.0032282201394698367,
            0.00871498751947037,
            -0.0032282201394698367,
            0.0,
            0.0,
            0.0
        ],
        [
            -0.0032282201394698367,
            -0.003228220139469837,
            0.00871498751947037,
            0.0,
            0.0,
            0.0
        ],
        [
            0.0,
            0.0,
            0.0,
            0.015478119897541037,
            0.0,
            0.0
        ],
        [
            0.0,
            0.0,
            0.0,
            0.0,
            0.015478119897541037,
            0.0
        ],
        [
            0.0,
            0.0,
            0.0,
            0.0,
            0.0,
            0.015478119897541037
        ]
    ],
    "dij": [
        [
            0.0,
            0.0,
            0.0,
            41.24315306018683,
            0.0,
            0.0
        ],
        [
            0.0,
            0.0,
            0.0,
            0.0,
            41.24315306018683,
            0.0
        ],
        [
            0.0,
            0.0,
            0.0,
            0.0,
            0.0,
            41.24315306018683
        ]
    ],
    "poisson": [
        0.37042165949837447,
        0.37042165949837447,
        0.37042165949837447
    ]
}